oitool/__init__.py
oitool/fetchoi.py
oitool-0.1.0.dist-info/LICENSE
oitool-0.1.0.dist-info/METADATA
oitool-0.1.0.dist-info/WHEEL
oitool-0.1.0.dist-info/top_level.txt
oitool-0.1.0.dist-info/RECORD
